Metadata-Version: 1.0
Name: lang-trans
Version: 0.4.0
Summary: Python transliteration library
Home-page: https://github.com/kariminf/lang-trans
Author: Abdelkrime Aries
Author-email: kariminfo0@gmail.com
License: Apache-2.0
Keywords: transliteration nlp languages romanization
Platform: UNKNOWN
